scs_hue-3.4.6.data/scripts/aws_client_auth.py
scs_hue-3.4.6.data/scripts/aws_mqtt_subscriber.py
scs_hue-3.4.6.data/scripts/bridge.py
scs_hue-3.4.6.data/scripts/bridge_address.py
scs_hue-3.4.6.data/scripts/channel_test.py
scs_hue-3.4.6.data/scripts/chroma.py
scs_hue-3.4.6.data/scripts/chroma_conf.py
scs_hue-3.4.6.data/scripts/desk.py
scs_hue-3.4.6.data/scripts/desk_conf.py
scs_hue-3.4.6.data/scripts/domain_conf.py
scs_hue-3.4.6.data/scripts/join.py
scs_hue-3.4.6.data/scripts/light.py
scs_hue-3.4.6.data/scripts/node.py
scs_hue-3.4.6.data/scripts/run_chroma.sh
scs_hue-3.4.6.data/scripts/uds_receiver.py
scs_hue-3.4.6.data/scripts/upnp_conf.py
scs_hue-3.4.6.data/scripts/user.py
scs_philips_hue/__init__.py
scs_philips_hue/aws_client_auth.py
scs_philips_hue/aws_mqtt_subscriber.py
scs_philips_hue/bridge.py
scs_philips_hue/bridge_address.py
scs_philips_hue/channel_test.py
scs_philips_hue/chroma.py
scs_philips_hue/chroma_conf.py
scs_philips_hue/desk.py
scs_philips_hue/desk_conf.py
scs_philips_hue/domain_conf.py
scs_philips_hue/join.py
scs_philips_hue/light.py
scs_philips_hue/node.py
scs_philips_hue/run_chroma.sh
scs_philips_hue/uds_receiver.py
scs_philips_hue/upnp_conf.py
scs_philips_hue/user.py
scs_philips_hue/client/__init__.py
scs_philips_hue/client/client_exception.py
scs_philips_hue/client/rest_client.py
scs_philips_hue/client/upnp_client.py
scs_philips_hue/cmd/__init__.py
scs_philips_hue/cmd/cmd_aws_client_auth.py
scs_philips_hue/cmd/cmd_bridge.py
scs_philips_hue/cmd/cmd_bridge_address.py
scs_philips_hue/cmd/cmd_channel_test.py
scs_philips_hue/cmd/cmd_chroma.py
scs_philips_hue/cmd/cmd_chroma_conf.py
scs_philips_hue/cmd/cmd_desk.py
scs_philips_hue/cmd/cmd_desk_conf.py
scs_philips_hue/cmd/cmd_domain_conf.py
scs_philips_hue/cmd/cmd_join.py
scs_philips_hue/cmd/cmd_light.py
scs_philips_hue/cmd/cmd_mqtt_subscriber.py
scs_philips_hue/cmd/cmd_node.py
scs_philips_hue/cmd/cmd_simple.py
scs_philips_hue/cmd/cmd_uds.py
scs_philips_hue/cmd/cmd_upnp_conf.py
scs_hue-3.4.6.dist-info/LICENSE
scs_hue-3.4.6.dist-info/METADATA
scs_hue-3.4.6.dist-info/WHEEL
scs_hue-3.4.6.dist-info/top_level.txt
scs_hue-3.4.6.dist-info/RECORD
